iso639/__init__.py
iso639/language.py
iso639/_data/__init__.py
iso639/_data/iso-639-3-macrolanguages.tab
iso639/_data/iso-639-3.tab
iso639/_data/iso-639-3_Name_Index.tab
iso639/_data/iso-639-3_Retirements.tab
python_iso639-2025.1.27.dist-info/LICENSE.txt
python_iso639-2025.1.27.dist-info/METADATA
python_iso639-2025.1.27.dist-info/WHEEL
python_iso639-2025.1.27.dist-info/top_level.txt
python_iso639-2025.1.27.dist-info/RECORD
