Metadata-Version: 2.2
Name: python-iso639
Version: 2025.1.27
Summary: ISO 639 language codes, names, and other associated information
Author-email: "Jackson L. Lee" <jacksonlunlee@gmail.com>
License: Apache 2.0
Project-URL: Source, https://github.com/jacksonllee/iso639
Keywords: ISO 639,language codes,languages,linguistics
Classifier: Development Status :: 5 - Production/Stable
Classifier: Intended Audience :: Developers
Classifier: Intended Audience :: Education
Classifier: Intended Audience :: Information Technology
Classifier: Intended Audience :: Science/Research
Classifier: License :: OSI Approved :: Apache Software License
Classifier: Operating System :: OS Independent
Classifier: Programming Language :: Python :: 3
Classifier: Programming Language :: Python :: 3 :: Only
Classifier: Programming Language :: Python :: 3.9
Classifier: Programming Language :: Python :: 3.10
Classifier: Programming Language :: Python :: 3.11
Classifier: Programming Language :: Python :: 3.12
Classifier: Programming Language :: Python :: 3.13
Classifier: Topic :: Text Processing
Classifier: Topic :: Text Processing :: General
Classifier: Topic :: Text Processing :: Indexing
Classifier: Topic :: Text Processing :: Linguistic
Requires-Python: >=3.9
License-File: LICENSE.txt
Provides-Extra: dev
Requires-Dist: black==24.10.0; extra == "dev"
Requires-Dist: build==1.2.2; extra == "dev"
Requires-Dist: flake8==7.1.1; extra == "dev"
Requires-Dist: mypy==1.14.1; extra == "dev"
Requires-Dist: pytest==8.3.4; extra == "dev"
Requires-Dist: requests==2.32.3; extra == "dev"
Requires-Dist: twine==6.1.0; extra == "dev"
